mylib_robo/__init__.py
mylib_robo/math_utils.py
mylib_robo/string_utils.py
mylib_robo-0.1.0.dist-info/METADATA
mylib_robo-0.1.0.dist-info/WHEEL
mylib_robo-0.1.0.dist-info/top_level.txt
mylib_robo-0.1.0.dist-info/RECORD
