Metadata-Version: 2.4
Name: mylib_robo
Version: 0.1.0
Summary: My custom Python library
Author: robotics
Requires-Python: >=3.8
